Growthaxl_sdk/Receive_data_from_bus.py
Growthaxl_sdk/Send_data_to_bus.py
Growthaxl_sdk/__init__.py
Growthaxl_sdk/filter_blockchain_response.py
Growthaxl_SDK-1.0.1.dist-info/LICENSE
Growthaxl_SDK-1.0.1.dist-info/METADATA
Growthaxl_SDK-1.0.1.dist-info/WHEEL
Growthaxl_SDK-1.0.1.dist-info/top_level.txt
Growthaxl_SDK-1.0.1.dist-info/RECORD
